{
    "Name": "家長むぎ",
    "Group": "nijisanjiJP",
    "data": {
        "01": {
            "median": 677,
            "average": 689,
            "streams": 6
        },
        "02": {
            "median": 696,
            "average": 799,
            "streams": 8
        },
        "03": {
            "median": null,
            "average": null,
            "streams": null
        },
        "04": {
            "median": null,
            "average": null,
            "streams": null
        },
        "05": {
            "median": null,
            "average": null,
            "streams": null
        },
        "06": {
            "median": null,
            "average": null,
            "streams": null
        },
        "07": {
            "median": null,
            "average": null,
            "streams": null
        },
        "08": {
            "median": null,
            "average": null,
            "streams": null
        },
        "09": {
            "median": null,
            "average": null,
            "streams": null
        },
        "10": {
            "median": null,
            "average": null,
            "streams": null
        },
        "11": {
            "median": null,
            "average": null,
            "streams": null
        },
        "12": {
            "median": null,
            "average": null,
            "streams": null
        }
    }
}